pydatagovgr/__init__.py
pydatagovgr/adapters.py
pydatagovgr/base_client.py
pydatagovgr/client.py
pydatagovgr/exceptions.py
pydatagovgr/session.py
pydatagovgr-1.0.1.dist-info/LICENSE
pydatagovgr-1.0.1.dist-info/METADATA
pydatagovgr-1.0.1.dist-info/WHEEL
pydatagovgr-1.0.1.dist-info/RECORD
