Metadata-Version: 2.3
Name: pydatagovgr
Version: 1.0.1
Summary: A Pythonic client for the official https://data.gov.gr API.
License: MIT
Keywords: client,pip,govgr,open-data
Author: ilias-ant
Author-email: ilias.antonopoulos@yahoo.gr
Requires-Python: >=3.9,<3.13
Classifier: Development Status :: 5 - Production/Stable
Classifier: Intended Audience :: Developers
Classifier: Intended Audience :: Education
Classifier: Intended Audience :: Information Technology
Classifier: Intended Audience :: Science/Research
Classifier: Natural Language :: English
Classifier: Natural Language :: Greek
Classifier: Operating System :: OS Independent
Classifier: Topic :: Software Development :: Libraries :: Python Modules
Classifier: Programming Language :: Python :: 3 :: Only
Requires-Dist: requests (>=2.32.4,<3.0.0)
Project-URL: Bug Tracker, https://github.com/ilias-ant/pydatagovgr/issues
Project-URL: Documentation, https://pydatagovgr.readthedocs.io
Project-URL: Homepage, https://pypi.org/project/pydatagovgr
Project-URL: Repository, https://github.com/ilias-ant/pydatagovgr
